ez_utils/__init__.py
ez_utils/decorators.py
ez_utils/file_utils.py
ez_utils/general.py
ez_utils/io_utils.py
ez_utils/lists.py
ez_utils-1.1.0.dist-info/METADATA
ez_utils-1.1.0.dist-info/WHEEL
ez_utils-1.1.0.dist-info/top_level.txt
ez_utils-1.1.0.dist-info/RECORD
