Metadata-Version: 2.1
Name: ez-utils
Version: 1.1.0
Summary: Some super simple one-liners to do common Python tasks
Home-page: https://www.github.com/nielsvaes/ez_utils
Author: Niels Vaes
Author-email: nielsvaes@gmail.com
License: MIT
Platform: UNKNOWN
